{"version":"1.2.0","artifactCoordinates":{"groupId":"com.mycompany","artifactId":"flight-pricing","version":"1.0.0-SNAPSHOT","type":"jar","classifier":"mule-application"},"dependencies":[{"artifactCoordinates":{"groupId":"com.amadeus","artifactId":"amadeus-java","version":"5.7.1","type":"jar"},"uri":"repository/com/amadeus/amadeus-java/5.7.1/amadeus-java-5.7.1.jar","packages":["com.amadeus","com.amadeus.airport.predictions","com.amadeus.analytics","com.amadeus.booking","com.amadeus.client","com.amadeus.ereputation","com.amadeus.exceptions","com.amadeus.media","com.amadeus.media.files","com.amadeus.referenceData","com.amadeus.referenceData.locations","com.amadeus.referenceData.locations.pointsOfInterest","com.amadeus.referenceData.urls","com.amadeus.resources","com.amadeus.safety","com.amadeus.safety.safetyRatedLocations","com.amadeus.schedule","com.amadeus.shopping","com.amadeus.shopping.activities","com.amadeus.shopping.flightOffers","com.amadeus.travel","com.amadeus.travel.analytics","com.amadeus.travel.analytics.airTraffic","com.amadeus.travel.predictions"],"resources":["META-INF/MANIFEST.MF"]},{"artifactCoordinates":{"groupId":"com.google.code.gson","artifactId":"gson","version":"2.8.6","type":"jar"},"uri":"repository/com/google/code/gson/gson/2.8.6/gson-2.8.6.jar","packages":["com.google.gson","com.google.gson.annotations","com.google.gson.internal","com.google.gson.internal.bind","com.google.gson.internal.bind.util","com.google.gson.internal.reflect","com.google.gson.reflect","com.google.gson.stream"],"resources":["META-INF/MANIFEST.MF","META-INF/maven/com.google.code.gson/gson/pom.properties","META-INF/maven/com.google.code.gson/gson/pom.xml"]},{"artifactCoordinates":{"groupId":"org.mule.connectors","artifactId":"mule-http-connector","version":"1.5.22","type":"jar","classifier":"mule-plugin"},"uri":"repository/org/mule/connectors/mule-http-connector/1.5.22/mule-http-connector-1.5.22-mule-plugin.jar"},{"artifactCoordinates":{"groupId":"org.mule.connectors","artifactId":"mule-sockets-connector","version":"1.2.0","type":"jar","classifier":"mule-plugin"},"uri":"repository/org/mule/connectors/mule-sockets-connector/1.2.0/mule-sockets-connector-1.2.0-mule-plugin.jar"},{"artifactCoordinates":{"groupId":"com.mashape.unirest","artifactId":"unirest-java","version":"1.4.9","type":"jar"},"uri":"repository/com/mashape/unirest/unirest-java/1.4.9/unirest-java-1.4.9.jar","packages":["com.mashape.unirest.http","com.mashape.unirest.http.async","com.mashape.unirest.http.async.utils","com.mashape.unirest.http.exceptions","com.mashape.unirest.http.options","com.mashape.unirest.http.utils","com.mashape.unirest.request","com.mashape.unirest.request.body"],"resources":["META-INF/MANIFEST.MF","META-INF/maven/com.mashape.unirest/unirest-java/pom.properties","META-INF/maven/com.mashape.unirest/unirest-java/pom.xml"]},{"artifactCoordinates":{"groupId":"org.apache.httpcomponents","artifactId":"httpclient","version":"4.5.2","type":"jar"},"uri":"repository/org/apache/httpcomponents/httpclient/4.5.2/httpclient-4.5.2.jar","packages":["org.apache.http.auth","org.apache.http.auth.params","org.apache.http.client","org.apache.http.client.config","org.apache.http.client.entity","org.apache.http.client.methods","org.apache.http.client.params","org.apache.http.client.protocol","org.apache.http.client.utils","org.apache.http.conn","org.apache.http.conn.params","org.apache.http.conn.routing","org.apache.http.conn.scheme","org.apache.http.conn.socket","org.apache.http.conn.ssl","org.apache.http.conn.util","org.apache.http.cookie","org.apache.http.cookie.params","org.apache.http.impl.auth","org.apache.http.impl.client","org.apache.http.impl.conn","org.apache.http.impl.conn.tsccm","org.apache.http.impl.cookie","org.apache.http.impl.execchain"],"resources":["META-INF/DEPENDENCIES","META-INF/LICENSE","META-INF/MANIFEST.MF","META-INF/NOTICE","META-INF/maven/org.apache.httpcomponents/httpclient/pom.properties","META-INF/maven/org.apache.httpcomponents/httpclient/pom.xml","mozilla/public-suffix-list.txt","org/apache/http/client/version.properties"]},{"artifactCoordinates":{"groupId":"org.apache.httpcomponents","artifactId":"httpcore","version":"4.4.4","type":"jar"},"uri":"repository/org/apache/httpcomponents/httpcore/4.4.4/httpcore-4.4.4.jar","packages":["org.apache.http","org.apache.http.annotation","org.apache.http.concurrent","org.apache.http.config","org.apache.http.entity","org.apache.http.impl","org.apache.http.impl.bootstrap","org.apache.http.impl.entity","org.apache.http.impl.io","org.apache.http.impl.pool","org.apache.http.io","org.apache.http.message","org.apache.http.params","org.apache.http.pool","org.apache.http.protocol","org.apache.http.ssl","org.apache.http.util"],"resources":["META-INF/DEPENDENCIES","META-INF/LICENSE","META-INF/MANIFEST.MF","META-INF/NOTICE","META-INF/maven/org.apache.httpcomponents/httpcore/pom.properties","META-INF/maven/org.apache.httpcomponents/httpcore/pom.xml","org/apache/http/version.properties"]},{"artifactCoordinates":{"groupId":"commons-logging","artifactId":"commons-logging","version":"1.2","type":"jar"},"uri":"repository/commons-logging/commons-logging/1.2/commons-logging-1.2.jar","packages":["org.apache.commons.logging","org.apache.commons.logging.impl"],"resources":["META-INF/LICENSE.txt","META-INF/MANIFEST.MF","META-INF/NOTICE.txt","META-INF/maven/commons-logging/commons-logging/pom.properties","META-INF/maven/commons-logging/commons-logging/pom.xml"]},{"artifactCoordinates":{"groupId":"commons-codec","artifactId":"commons-codec","version":"1.9","type":"jar"},"uri":"repository/commons-codec/commons-codec/1.9/commons-codec-1.9.jar","packages":["org.apache.commons.codec","org.apache.commons.codec.binary","org.apache.commons.codec.digest","org.apache.commons.codec.language","org.apache.commons.codec.language.bm","org.apache.commons.codec.net"],"resources":["META-INF/LICENSE.txt","META-INF/MANIFEST.MF","META-INF/NOTICE.txt","META-INF/maven/commons-codec/commons-codec/pom.properties","META-INF/maven/commons-codec/commons-codec/pom.xml","org/apache/commons/codec/language/bm/ash_approx_any.txt","org/apache/commons/codec/language/bm/ash_approx_common.txt","org/apache/commons/codec/language/bm/ash_approx_cyrillic.txt","org/apache/commons/codec/language/bm/ash_approx_english.txt","org/apache/commons/codec/language/bm/ash_approx_french.txt","org/apache/commons/codec/language/bm/ash_approx_german.txt","org/apache/commons/codec/language/bm/ash_approx_hebrew.txt","org/apache/commons/codec/language/bm/ash_approx_hungarian.txt","org/apache/commons/codec/language/bm/ash_approx_polish.txt","org/apache/commons/codec/language/bm/ash_approx_romanian.txt","org/apache/commons/codec/language/bm/ash_approx_russian.txt","org/apache/commons/codec/language/bm/ash_approx_spanish.txt","org/apache/commons/codec/language/bm/ash_exact_any.txt","org/apache/commons/codec/language/bm/ash_exact_approx_common.txt","org/apache/commons/codec/language/bm/ash_exact_common.txt","org/apache/commons/codec/language/bm/ash_exact_cyrillic.txt","org/apache/commons/codec/language/bm/ash_exact_english.txt","org/apache/commons/codec/language/bm/ash_exact_french.txt","org/apache/commons/codec/language/bm/ash_exact_german.txt","org/apache/commons/codec/language/bm/ash_exact_hebrew.txt","org/apache/commons/codec/language/bm/ash_exact_hungarian.txt","org/apache/commons/codec/language/bm/ash_exact_polish.txt","org/apache/commons/codec/language/bm/ash_exact_romanian.txt","org/apache/commons/codec/language/bm/ash_exact_russian.txt","org/apache/commons/codec/language/bm/ash_exact_spanish.txt","org/apache/commons/codec/language/bm/ash_hebrew_common.txt","org/apache/commons/codec/language/bm/ash_languages.txt","org/apache/commons/codec/language/bm/ash_rules_any.txt","org/apache/commons/codec/language/bm/ash_rules_cyrillic.txt","org/apache/commons/codec/language/bm/ash_rules_english.txt","org/apache/commons/codec/language/bm/ash_rules_french.txt","org/apache/commons/codec/language/bm/ash_rules_german.txt","org/apache/commons/codec/language/bm/ash_rules_hebrew.txt","org/apache/commons/codec/language/bm/ash_rules_hungarian.txt","org/apache/commons/codec/language/bm/ash_rules_polish.txt","org/apache/commons/codec/language/bm/ash_rules_romanian.txt","org/apache/commons/codec/language/bm/ash_rules_russian.txt","org/apache/commons/codec/language/bm/ash_rules_spanish.txt","org/apache/commons/codec/language/bm/gen_approx_any.txt","org/apache/commons/codec/language/bm/gen_approx_arabic.txt","org/apache/commons/codec/language/bm/gen_approx_common.txt","org/apache/commons/codec/language/bm/gen_approx_cyrillic.txt","org/apache/commons/codec/language/bm/gen_approx_czech.txt","org/apache/commons/codec/language/bm/gen_approx_dutch.txt","org/apache/commons/codec/language/bm/gen_approx_english.txt","org/apache/commons/codec/language/bm/gen_approx_french.txt","org/apache/commons/codec/language/bm/gen_approx_german.txt","org/apache/commons/codec/language/bm/gen_approx_greek.txt","org/apache/commons/codec/language/bm/gen_approx_greeklatin.txt","org/apache/commons/codec/language/bm/gen_approx_hebrew.txt","org/apache/commons/codec/language/bm/gen_approx_hungarian.txt","org/apache/commons/codec/language/bm/gen_approx_italian.txt","org/apache/commons/codec/language/bm/gen_approx_polish.txt","org/apache/commons/codec/language/bm/gen_approx_portuguese.txt","org/apache/commons/codec/language/bm/gen_approx_romanian.txt","org/apache/commons/codec/language/bm/gen_approx_russian.txt","org/apache/commons/codec/language/bm/gen_approx_spanish.txt","org/apache/commons/codec/language/bm/gen_approx_turkish.txt","org/apache/commons/codec/language/bm/gen_exact_any.txt","org/apache/commons/codec/language/bm/gen_exact_approx_common.txt","org/apache/commons/codec/language/bm/gen_exact_arabic.txt","org/apache/commons/codec/language/bm/gen_exact_common.txt","org/apache/commons/codec/language/bm/gen_exact_cyrillic.txt","org/apache/commons/codec/language/bm/gen_exact_czech.txt","org/apache/commons/codec/language/bm/gen_exact_dutch.txt","org/apache/commons/codec/language/bm/gen_exact_english.txt","org/apache/commons/codec/language/bm/gen_exact_french.txt","org/apache/commons/codec/language/bm/gen_exact_german.txt","org/apache/commons/codec/language/bm/gen_exact_greek.txt","org/apache/commons/codec/language/bm/gen_exact_greeklatin.txt","org/apache/commons/codec/language/bm/gen_exact_hebrew.txt","org/apache/commons/codec/language/bm/gen_exact_hungarian.txt","org/apache/commons/codec/language/bm/gen_exact_italian.txt","org/apache/commons/codec/language/bm/gen_exact_polish.txt","org/apache/commons/codec/language/bm/gen_exact_portuguese.txt","org/apache/commons/codec/language/bm/gen_exact_romanian.txt","org/apache/commons/codec/language/bm/gen_exact_russian.txt","org/apache/commons/codec/language/bm/gen_exact_spanish.txt","org/apache/commons/codec/language/bm/gen_exact_turkish.txt","org/apache/commons/codec/language/bm/gen_hebrew_common.txt","org/apache/commons/codec/language/bm/gen_languages.txt","org/apache/commons/codec/language/bm/gen_rules_any.txt","org/apache/commons/codec/language/bm/gen_rules_arabic.txt","org/apache/commons/codec/language/bm/gen_rules_cyrillic.txt","org/apache/commons/codec/language/bm/gen_rules_czech.txt","org/apache/commons/codec/language/bm/gen_rules_dutch.txt","org/apache/commons/codec/language/bm/gen_rules_english.txt","org/apache/commons/codec/language/bm/gen_rules_french.txt","org/apache/commons/codec/language/bm/gen_rules_german.txt","org/apache/commons/codec/language/bm/gen_rules_greek.txt","org/apache/commons/codec/language/bm/gen_rules_greeklatin.txt","org/apache/commons/codec/language/bm/gen_rules_hebrew.txt","org/apache/commons/codec/language/bm/gen_rules_hungarian.txt","org/apache/commons/codec/language/bm/gen_rules_italian.txt","org/apache/commons/codec/language/bm/gen_rules_polish.txt","org/apache/commons/codec/language/bm/gen_rules_portuguese.txt","org/apache/commons/codec/language/bm/gen_rules_romanian.txt","org/apache/commons/codec/language/bm/gen_rules_russian.txt","org/apache/commons/codec/language/bm/gen_rules_spanish.txt","org/apache/commons/codec/language/bm/gen_rules_turkish.txt","org/apache/commons/codec/language/bm/lang.txt","org/apache/commons/codec/language/bm/sep_approx_any.txt","org/apache/commons/codec/language/bm/sep_approx_common.txt","org/apache/commons/codec/language/bm/sep_approx_french.txt","org/apache/commons/codec/language/bm/sep_approx_hebrew.txt","org/apache/commons/codec/language/bm/sep_approx_italian.txt","org/apache/commons/codec/language/bm/sep_approx_portuguese.txt","org/apache/commons/codec/language/bm/sep_approx_spanish.txt","org/apache/commons/codec/language/bm/sep_exact_any.txt","org/apache/commons/codec/language/bm/sep_exact_approx_common.txt","org/apache/commons/codec/language/bm/sep_exact_common.txt","org/apache/commons/codec/language/bm/sep_exact_french.txt","org/apache/commons/codec/language/bm/sep_exact_hebrew.txt","org/apache/commons/codec/language/bm/sep_exact_italian.txt","org/apache/commons/codec/language/bm/sep_exact_portuguese.txt","org/apache/commons/codec/language/bm/sep_exact_spanish.txt","org/apache/commons/codec/language/bm/sep_hebrew_common.txt","org/apache/commons/codec/language/bm/sep_languages.txt","org/apache/commons/codec/language/bm/sep_rules_any.txt","org/apache/commons/codec/language/bm/sep_rules_french.txt","org/apache/commons/codec/language/bm/sep_rules_hebrew.txt","org/apache/commons/codec/language/bm/sep_rules_italian.txt","org/apache/commons/codec/language/bm/sep_rules_portuguese.txt","org/apache/commons/codec/language/bm/sep_rules_spanish.txt"]},{"artifactCoordinates":{"groupId":"org.apache.httpcomponents","artifactId":"httpasyncclient","version":"4.1.1","type":"jar"},"uri":"repository/org/apache/httpcomponents/httpasyncclient/4.1.1/httpasyncclient-4.1.1.jar","packages":["org.apache.http.impl.nio.client","org.apache.http.impl.nio.conn","org.apache.http.nio.client","org.apache.http.nio.client.methods","org.apache.http.nio.client.util","org.apache.http.nio.conn","org.apache.http.nio.conn.scheme","org.apache.http.nio.conn.ssl"],"resources":["META-INF/DEPENDENCIES","META-INF/LICENSE","META-INF/MANIFEST.MF","META-INF/NOTICE","META-INF/maven/org.apache.httpcomponents/httpasyncclient/pom.properties","META-INF/maven/org.apache.httpcomponents/httpasyncclient/pom.xml","org/apache/http/nio/client/version.properties"]},{"artifactCoordinates":{"groupId":"org.apache.httpcomponents","artifactId":"httpcore-nio","version":"4.4.4","type":"jar"},"uri":"repository/org/apache/httpcomponents/httpcore-nio/4.4.4/httpcore-nio-4.4.4.jar","packages":["org.apache.http.impl.nio","org.apache.http.impl.nio.bootstrap","org.apache.http.impl.nio.codecs","org.apache.http.impl.nio.pool","org.apache.http.impl.nio.reactor","org.apache.http.impl.nio.ssl","org.apache.http.nio","org.apache.http.nio.entity","org.apache.http.nio.params","org.apache.http.nio.pool","org.apache.http.nio.protocol","org.apache.http.nio.reactor","org.apache.http.nio.reactor.ssl","org.apache.http.nio.util"],"resources":["META-INF/DEPENDENCIES","META-INF/LICENSE","META-INF/MANIFEST.MF","META-INF/NOTICE","META-INF/maven/org.apache.httpcomponents/httpcore-nio/pom.properties","META-INF/maven/org.apache.httpcomponents/httpcore-nio/pom.xml","org/apache/http/nio/version.properties"]},{"artifactCoordinates":{"groupId":"org.apache.httpcomponents","artifactId":"httpmime","version":"4.5.2","type":"jar"},"uri":"repository/org/apache/httpcomponents/httpmime/4.5.2/httpmime-4.5.2.jar","packages":["org.apache.http.entity.mime","org.apache.http.entity.mime.content"],"resources":["META-INF/DEPENDENCIES","META-INF/LICENSE","META-INF/MANIFEST.MF","META-INF/NOTICE","META-INF/maven/org.apache.httpcomponents/httpmime/pom.properties","META-INF/maven/org.apache.httpcomponents/httpmime/pom.xml","org/apache/http/entity/mime/version.properties"]},{"artifactCoordinates":{"groupId":"org.json","artifactId":"json","version":"20160212","type":"jar"},"uri":"repository/org/json/json/20160212/json-20160212.jar","packages":["org.json"],"resources":["META-INF/MANIFEST.MF","META-INF/maven/org.json/json/pom.properties","META-INF/maven/org.json/json/pom.xml"]}]}